README.md
setup.py
docutrance/__init__.py
docutrance/generate.py
docutrance/index.py
docutrance/preprocess.py
docutrance/search.py
docutrance/util.py
docutrance/ux.py
docutrance.egg-info/PKG-INFO
docutrance.egg-info/SOURCES.txt
docutrance.egg-info/dependency_links.txt
docutrance.egg-info/requires.txt
docutrance.egg-info/top_level.txt