Metadata-Version: 2.4
Name: docutrance
Version: 0.4.0
Summary: A short description of your package
Home-page: https://github.com/Lone-Wolfgang/multilingual-retriever-for-milton-h-erickson
Author: Jordan Wolfgang Klein
Author-email: jwklein14@gmail.com
License: Apache-2.0
Classifier: Programming Language :: Python :: 3
Classifier: License :: OSI Approved :: Apache Software License
Classifier: Operating System :: OS Independent
Requires-Python: >=3.10
Requires-Dist: deepdiff
Requires-Dist: streamlit
Requires-Dist: opensearch-py
Requires-Dist: spacy
Requires-Dist: spacy-udpipe
Requires-Dist: pymupdf4llm
Requires-Dist: pypandoc
Requires-Dist: tqdm
Requires-Dist: sentence-transformers
Requires-Dist: wandb
Requires-Dist: optuna
Requires-Dist: datasets
Requires-Dist: openpyxl
Requires-Dist: pandas
Requires-Dist: matplotlib
Requires-Dist: transformers
Requires-Dist: transformers[torch]
Requires-Dist: wikipedia
Requires-Dist: twine
Dynamic: author
Dynamic: author-email
Dynamic: classifier
Dynamic: description-content-type
Dynamic: home-page
Dynamic: license
Dynamic: requires-dist
Dynamic: requires-python
Dynamic: summary
